anfs/__init__.py
anfs/_version.py
anfs/examples/__init__.py
anfs/examples/anfsclient.py
anfs/examples/utils/__init__.py
anfs/external/__init__.py
anfs/external/aiocmd/__init__.py
anfs/external/aiocmd/aiocmd/__init__.py
anfs/external/aiocmd/aiocmd/aiocmd.py
anfs/external/aiocmd/aiocmd/nested_completer.py
anfs/external/asciitree/__init__.py
anfs/external/asciitree/setup.py
anfs/external/asciitree/asciitree/__init__.py
anfs/external/asciitree/asciitree/drawing.py
anfs/external/asciitree/asciitree/traversal.py
anfs/external/asciitree/asciitree/util.py
anfs/protocol/__init__.py
anfs/protocol/mount/__init__.py
anfs/protocol/mount/messages.py
anfs/protocol/nfs3/__init__.py
anfs/protocol/nfs3/client.py
anfs/protocol/nfs3/messages.py
anfs/protocol/nfs3/pack.py
anfs/protocol/nfs3/rtypes.py
anfs/protocol/nfs3/common/__init__.py
anfs/protocol/nfs3/common/factory.py
anfs/protocol/portmap/__init__.py
anfs/protocol/portmap/messages.py
anfs/protocol/portmap/parser.py
anfs/protocol/portmap/wellknown.py
anfs/protocol/rpc/__init__.py
anfs/protocol/rpc/messages.py
anfs/protocol/rpc/packetizer.py
anfs/protocol/rpc/common/__init__.py
anfs/protocol/rpc/common/exceptions.py
anfs/protocol/rpc/common/target.py
anfs/utils/__init__.py
anfs/utils/enumerator.py
anfs-0.0.3.dist-info/LICENSE
anfs-0.0.3.dist-info/METADATA
anfs-0.0.3.dist-info/WHEEL
anfs-0.0.3.dist-info/entry_points.txt
anfs-0.0.3.dist-info/top_level.txt
anfs-0.0.3.dist-info/RECORD
